[{"url_token": "wang-xiao-zhi-30", "headline": "", "is_advertiser": false, "comment_id": "186573982", "reply_comment_id": "0", "reply_root_comment_id": "186573982", "hot": false, "is_author": false, "is_author_top": false, "content": "老舍先生：“臭豆腐滴几滴香油，可以招待姑奶奶”", "like_count": 5, "author_name": "王小知", "author_id": "8573f3ebf988449ff9b63f705b3facf1", "author_is_anonymous": false, "child_comment": [{"url_token": "xiao-ao-jiang-hu-25-91", "headline": "市井之徒，放浪形骸", "is_advertiser": false, "comment_id": "186939455", "reply_comment_id": "186573982", "reply_root_comment_id": "186573982", "hot": false, "is_author": false, "is_author_top": false, "content": "哦?哈哈！", "like_count": 0, "author_name": "南城市井之徒", "author_id": "bb2976cbfbb1e3bd211fab84eca30666", "author_is_anonymous": false}]}, {"url_token": "fen-hong-zhu-xiao-di", "headline": "不加狗头是对网友智力水平的信任。", "is_advertiser": false, "comment_id": "424131400", "reply_comment_id": "0", "reply_root_comment_id": "424131400", "hot": false, "is_author": false, "is_author_top": false, "content": "没有店专卖做这个，菜单上也不会写。但是地道点的涮肉、卤煮和羊蝎子店里，只要跟人说一般都会有。", "like_count": 2, "author_name": "粉红猪小弟", "author_id": "ce604d539244619dd6b3ff506f806125", "author_is_anonymous": false, "child_comment": []}, {"url_token": "pan-li-zi-82", "headline": "Smail,like the sunshine", "is_advertiser": false, "comment_id": "425703937", "reply_comment_id": "0", "reply_root_comment_id": "425703937", "hot": false, "is_author": false, "is_author_top": false, "content": "<p>馒头片煎一下，抹臭豆腐同理</p>", "like_count": 1, "author_name": "潘栗子", "author_id": "bbc57ef62e9dcad70a7a8961e711d6d5", "author_is_anonymous": false, "child_comment": []}, {"url_token": "glenfiddich-20", "headline": "", "is_advertiser": false, "comment_id": "554009699", "reply_comment_id": "0", "reply_root_comment_id": "554009699", "hot": false, "is_author": false, "is_author_top": false, "content": "吃羊蝎子有幸尝过，打算回了老家给父母试试", "like_count": 0, "author_name": "Glenfiddich", "author_id": "70785068ddd1333f7669ff15684447fb", "author_is_anonymous": false, "child_comment": []}, {"url_token": "jiang-yue-94-29", "headline": "", "is_advertiser": false, "comment_id": "443580461", "reply_comment_id": "0", "reply_root_comment_id": "443580461", "hot": false, "is_author": false, "is_author_top": false, "content": "好像王茜华的哪个电视剧里有这么吃。", "like_count": 0, "author_name": "江月", "author_id": "780c34133352691147fa5d326c412ddb", "author_is_anonymous": false, "child_comment": []}, {"url_token": "tian-yu-3-14", "headline": "请恕我直怼", "is_advertiser": false, "comment_id": "424433273", "reply_comment_id": "0", "reply_root_comment_id": "424433273", "hot": false, "is_author": false, "is_author_top": false, "content": "<p>对！有一种无法形容的好吃！超级好吃！（擦口水</p>", "like_count": 0, "author_name": "檰羊卷", "author_id": "8a87884739ec06d1088084dedba61c54", "author_is_anonymous": false, "child_comment": []}, {"url_token": "zydrate", "headline": "大葉餃子おおバカ", "is_advertiser": false, "comment_id": "424140101", "reply_comment_id": "0", "reply_root_comment_id": "424140101", "hot": false, "is_author": false, "is_author_top": false, "content": "<p>这就是传说中的炸窝头？我在爆肚店看到过，没点。</p>", "like_count": 0, "author_name": "空腹虫", "author_id": "4ad25b8e2a748e7fdd7f31f7ee98062e", "author_is_anonymous": false, "child_comment": []}, {"url_token": "yige-zei-6de-lu-ren", "headline": "骂完就拉黑的都是废物，有本事战个痛快？", "is_advertiser": false, "comment_id": "423984877", "reply_comment_id": "0", "reply_root_comment_id": "423984877", "hot": false, "is_author": false, "is_author_top": false, "content": "黑科技！", "like_count": 0, "author_name": "一个贼6的路人", "author_id": "4e1958e8e9ef6d43cff8c9597efd8bdd", "author_is_anonymous": false, "child_comment": []}, {"url_token": "xiao-yan-37-75", "headline": "假装是个酷人", "is_advertiser": false, "comment_id": "423972962", "reply_comment_id": "0", "reply_root_comment_id": "423972962", "hot": false, "is_author": false, "is_author_top": false, "content": "听起来不错呀~还没试过臭豆腐呢", "like_count": 0, "author_name": "不管", "author_id": "ac83e3957c9acbf37da07692ae17b813", "author_is_anonymous": false, "child_comment": []}, {"url_token": "wu-wu-wu-wu-34-92", "headline": "信息安全技术，打酱油的", "is_advertiser": false, "comment_id": "423925673", "reply_comment_id": "0", "reply_root_comment_id": "423925673", "hot": false, "is_author": false, "is_author_top": false, "content": "又想吃，又觉得是黑暗料理", "like_count": 0, "author_name": "仵呜呜呜", "author_id": "8fe2fdbf105ff1ea49255f86297e4536", "author_is_anonymous": false, "child_comment": []}]