[{"url_token": "mu-jiang-78-70", "headline": "茫然探索者", "is_advertiser": false, "comment_id": "1060096019", "reply_comment_id": "0", "reply_root_comment_id": "1060096019", "hot": false, "is_author": false, "is_author_top": false, "content": "做自己喜欢的事儿，潇洒", "like_count": 0, "author_name": "木茳", "author_id": "e276ea84dac8a95017486062ac9be9f9", "author_is_anonymous": false, "child_comment": [{"url_token": "yu-yuan-wan-zi-zhou", "headline": "努力工作是为了用心生活", "is_advertiser": false, "comment_id": "1060104144", "reply_comment_id": "1060096019", "reply_root_comment_id": "1060096019", "hot": false, "is_author": false, "is_author_top": false, "content": "[赞同][爱][爱][爱][爱]", "like_count": 0, "author_name": "芋圆丸子粥", "author_id": "8421e4c5e97e3665943f61dd50049312", "author_is_anonymous": false}]}, {"url_token": "rita-77-12-8", "headline": "一个爱美的吃货沙雕美少女哈哈哈", "is_advertiser": false, "comment_id": "1060056087", "reply_comment_id": "0", "reply_root_comment_id": "1060056087", "hot": false, "is_author": false, "is_author_top": false, "content": "喜欢你这样性格直爽的姐妹！你好好看啊", "like_count": 0, "author_name": "Rita", "author_id": "6a5ab1ee7ce1885c36bb14daa6c798e4", "author_is_anonymous": false, "child_comment": [{"url_token": "yu-yuan-wan-zi-zhou", "headline": "努力工作是为了用心生活", "is_advertiser": false, "comment_id": "1060057187", "reply_comment_id": "1060056087", "reply_root_comment_id": "1060056087", "hot": false, "is_author": false, "is_author_top": false, "content": "做自己喜欢的事情[爱][爱][爱]", "like_count": 0, "author_name": "芋圆丸子粥", "author_id": "8421e4c5e97e3665943f61dd50049312", "author_is_anonymous": false}]}, {"url_token": "mountain_human", "headline": "Manners makth man!", "is_advertiser": false, "comment_id": "1059838222", "reply_comment_id": "0", "reply_root_comment_id": "1059838222", "hot": false, "is_author": false, "is_author_top": false, "content": "<p>确认过眼神，我遇上对的人，不得不承认，想请你喝奶茶！</p><a class=\"comment_sticker\" href=\"https://pic3.zhimg.com/v2-cb8443f07a41298e45191cef11b90fd2.gif\" data-width=\"\" data-height=\"\">[干杯]</a>", "like_count": 0, "author_name": "PuppyTek", "author_id": "8a1293df40641e23d26ba7a9e936023d", "author_is_anonymous": false, "child_comment": []}, {"url_token": "wo-shi-sen-lin-2", "headline": "学生", "is_advertiser": false, "comment_id": "1059796172", "reply_comment_id": "0", "reply_root_comment_id": "1059796172", "hot": false, "is_author": false, "is_author_top": false, "content": "好漂亮！！！我爱美女", "like_count": 0, "author_name": "我是森林", "author_id": "bcea9f9871430a13c51710ced3d95c42", "author_is_anonymous": false, "child_comment": [{"url_token": "yu-yuan-wan-zi-zhou", "headline": "努力工作是为了用心生活", "is_advertiser": false, "comment_id": "1060054856", "reply_comment_id": "1059796172", "reply_root_comment_id": "1059796172", "hot": false, "is_author": false, "is_author_top": false, "content": "[爱][爱]", "like_count": 0, "author_name": "芋圆丸子粥", "author_id": "8421e4c5e97e3665943f61dd50049312", "author_is_anonymous": false}]}]