[{"url_token": "zhou-kai-66-19", "headline": "脱离了高级趣味的为的对人民无害生物", "is_advertiser": false, "comment_id": "1244861271", "reply_comment_id": "0", "reply_root_comment_id": "1244861271", "hot": false, "is_author": false, "is_author_top": false, "content": "新手正常 老手开好一点的车简直不要太爽", "like_count": 0, "author_name": "梨涡浅笑", "author_id": "cf70c499affebea42555b0324a6ddff7", "author_is_anonymous": false, "child_comment": []}, {"url_token": "ha-ha-ha-90-70-7", "headline": "", "is_advertiser": false, "comment_id": "1241793297", "reply_comment_id": "0", "reply_root_comment_id": "1241793297", "hot": false, "is_author": false, "is_author_top": false, "content": "害怕改成可怕", "like_count": 0, "author_name": "哈哈哈", "author_id": "57d447f432ec60f9b7dcbc0fb86a4edf", "author_is_anonymous": false, "child_comment": []}]