[{"url_token": "wo-de-tian-kong-97-47", "headline": "可以抬杠，别互相伤害。", "is_advertiser": false, "comment_id": "3051856589", "reply_comment_id": "0", "reply_root_comment_id": "3051856589", "hot": false, "is_author": false, "is_author_top": false, "content": "新车上牌手续自己都搞不定，估计小学都是混下来的。还是不要开车了。只要正规渠道买的新车。除去排队时间，半小时办好都是拖延时间。", "like_count": 5, "author_name": "我的天空", "author_id": "d0b0fa4704bc1c06f1522da60211a9bd", "author_is_anonymous": false, "child_comment": [{"url_token": "kong-xiang-xu-67-23", "headline": "汽车主机厂的智能驾驶开发人员", "is_advertiser": false, "comment_id": "3140987480", "reply_comment_id": "3051856589", "reply_root_comment_id": "3051856589", "hot": false, "is_author": false, "is_author_top": false, "content": "花钱找人帮自己办事，享受这种服务不香嘛，自己在那查来查去的，还得排队，请假，看人脸色", "like_count": 3, "author_name": "你的小泡泡", "author_id": "d849e82ba5b23aa0de61010e21923785", "author_is_anonymous": false}, {"url_token": "zhang-shi-lin-42-31", "headline": "", "is_advertiser": false, "comment_id": "3136066729", "reply_comment_id": "3051856589", "reply_root_comment_id": "3051856589", "hot": false, "is_author": false, "is_author_top": false, "content": "我就是自己班的上牌，新手，第二天开车就去上牌了，哈哈哈，去之前把所有的东西准备好，特快，算上等待时间也就一小时[捂脸]", "like_count": 2, "author_name": "疯狂年华", "author_id": "5b5ee8c9db167b93e9028af556461752", "author_is_anonymous": false}, {"url_token": "yong-xun-46", "headline": "寻寻觅觅", "is_advertiser": false, "comment_id": "3095746494", "reply_comment_id": "3051856589", "reply_root_comment_id": "3051856589", "hot": false, "is_author": false, "is_author_top": false, "content": "哈哈是的，黄牛就是赚的信息差。毕竟买车是大宗消费，属于不常办的业务，很多人不了解流程以为很难。", "like_count": 1, "author_name": "永寻", "author_id": "246aedd1d63b57c26c2625faaf2ed1ee", "author_is_anonymous": false}, {"url_token": "zhao-xie-32", "headline": "", "is_advertiser": false, "comment_id": "3186827167", "reply_comment_id": "3051856589", "reply_root_comment_id": "3051856589", "hot": false, "is_author": false, "is_author_top": false, "content": "我当时想的是上牌得请假，得扣全勤不值得，而且驾驶本下来都没摸过车，怕路上撞了得不偿失，再就是的确也担心万一一天因为流程不熟办不下来的问题，不错最后被车管所热心大哥摇到了一个不错的号，全当花800块买了哈哈哈，还是很值的", "like_count": 0, "author_name": "知乎用户91aak4", "author_id": "f8342043b3059931c29bc0914cfc511b", "author_is_anonymous": false}, {"url_token": "kong-xiang-xu-67-23", "headline": "汽车主机厂的智能驾驶开发人员", "is_advertiser": false, "comment_id": "3163818938", "reply_comment_id": "3160455820", "reply_root_comment_id": "3051856589", "hot": false, "is_author": false, "is_author_top": false, "content": "在知乎，必须得打肿脸充胖子", "like_count": 0, "author_name": "你的小泡泡", "author_id": "d849e82ba5b23aa0de61010e21923785", "author_is_anonymous": false}, {"url_token": "tu-hao-75-40", "headline": "", "is_advertiser": false, "comment_id": "3160455820", "reply_comment_id": "3140987480", "reply_root_comment_id": "3051856589", "hot": false, "is_author": false, "is_author_top": false, "content": "有钱人就是不一样。[大笑]", "like_count": 0, "author_name": "土嚎", "author_id": "c3e400331f1c016aa80e222c105f2f13", "author_is_anonymous": false}]}, {"url_token": "wen-dao-83-76-12", "headline": "", "is_advertiser": false, "comment_id": "3111135936", "reply_comment_id": "0", "reply_root_comment_id": "3111135936", "hot": false, "is_author": false, "is_author_top": false, "content": "保险怎么可能过期，到期前两个月会被各个保险公司的报价电话轮番轰炸", "like_count": 3, "author_name": "问道", "author_id": "6d1318badb34d21546462c235352ffdf", "author_is_anonymous": false, "child_comment": [{"url_token": "yong-xun-46", "headline": "寻寻觅觅", "is_advertiser": false, "comment_id": "3114495959", "reply_comment_id": "3111135936", "reply_root_comment_id": "3111135936", "hot": false, "is_author": false, "is_author_top": false, "content": "确实是...不过办公室有个同事就没管那些电话，最初接电话觉得过期时间还长，就放着没管...一直过期了两个多月，直到一次事故", "like_count": 2, "author_name": "永寻", "author_id": "246aedd1d63b57c26c2625faaf2ed1ee", "author_is_anonymous": false}]}, {"url_token": "chen-meng-56-54", "headline": "喵了个喵", "is_advertiser": false, "comment_id": "3168526906", "reply_comment_id": "0", "reply_root_comment_id": "3168526906", "hot": false, "is_author": false, "is_author_top": false, "content": "我都30啦，还在开手动档的捷达，我流下了沧桑的泪水", "like_count": 1, "author_name": "小白兔兔兔", "author_id": "b6a3b49c95aa0bebb79f5236218f11a8", "author_is_anonymous": false, "child_comment": []}, {"url_token": "bo-cai-13-30", "headline": "晒不黑", "is_advertiser": false, "comment_id": "3124755782", "reply_comment_id": "0", "reply_root_comment_id": "3124755782", "hot": false, "is_author": false, "is_author_top": false, "content": "同狗夫7·5阿蓝[捂嘴]", "like_count": 1, "author_name": "菠菜", "author_id": "cb64e24ff4f671556e84c1ad4ccc6fbd", "author_is_anonymous": false, "child_comment": []}, {"url_token": "li-xi-le-11", "headline": "数码爱好", "is_advertiser": false, "comment_id": "3110596242", "reply_comment_id": "0", "reply_root_comment_id": "3110596242", "hot": false, "is_author": false, "is_author_top": false, "content": "十次车祸九次快不适用于高速…", "like_count": 1, "author_name": "理性操作", "author_id": "2a1ff4c5db6078f05551c60ad75d4d69", "author_is_anonymous": false, "child_comment": [{"url_token": "yong-xun-46", "headline": "寻寻觅觅", "is_advertiser": false, "comment_id": "3113836403", "reply_comment_id": "3110596242", "reply_root_comment_id": "3110596242", "hot": false, "is_author": false, "is_author_top": false, "content": "[赞]说的对，高速没考虑到", "like_count": 1, "author_name": "永寻", "author_id": "246aedd1d63b57c26c2625faaf2ed1ee", "author_is_anonymous": false}]}, {"url_token": "wo-jiu-shi-wo-28-19", "headline": "IT", "is_advertiser": false, "comment_id": "3103635981", "reply_comment_id": "0", "reply_root_comment_id": "3103635981", "hot": false, "is_author": false, "is_author_top": false, "content": "代上牌就是省时间<br>缴税+上牌，最快也要一天。<br>几百块钱人不用到场不也挺好…", "like_count": 1, "author_name": "我就是我", "author_id": "5d3c661d7c66f38caf2570cb20b859b3", "author_is_anonymous": false, "child_comment": [{"url_token": "yong-xun-46", "headline": "寻寻觅觅", "is_advertiser": false, "comment_id": "3103246487", "reply_comment_id": "3103635981", "reply_root_comment_id": "3103635981", "hot": false, "is_author": false, "is_author_top": false, "content": "对，时间不方便的话只能找人代办了。时间宽裕的稍微了解下流程就自己办吧[大笑]提前做下流程的功课，有些地方半天能办下来", "like_count": 1, "author_name": "永寻", "author_id": "246aedd1d63b57c26c2625faaf2ed1ee", "author_is_anonymous": false}]}, {"url_token": "mao-ke-leo", "headline": "", "is_advertiser": false, "comment_id": "4809064628", "reply_comment_id": "0", "reply_root_comment_id": "4809064628", "hot": false, "is_author": false, "is_author_top": false, "content": "喜提4S店千元上牌服务[捂脸][捂脸][捂脸]", "like_count": 0, "author_name": "猫科leo", "author_id": "bed8f2c08186feb0191b3e3fc11ede0a", "author_is_anonymous": false, "child_comment": []}, {"url_token": "ji-sheng-90-41", "headline": "", "is_advertiser": false, "comment_id": "3441436257", "reply_comment_id": "0", "reply_root_comment_id": "3441436257", "hot": false, "is_author": false, "is_author_top": false, "content": "以前感觉开五菱宏光很舒服，自从开了其它车子后，发现五菱座椅太硬了，没有对比就没有伤害", "like_count": 0, "author_name": "小季同学", "author_id": "1d21d84766bf9793420c0fcf68318ef5", "author_is_anonymous": false, "child_comment": []}, {"url_token": "gta6-72", "headline": "", "is_advertiser": false, "comment_id": "3199456212", "reply_comment_id": "0", "reply_root_comment_id": "3199456212", "hot": false, "is_author": false, "is_author_top": false, "content": "租过最新款的XC90，gl8，怎么说呢，那些最新配置，反而影响我开车。车道保持，还得给关了再开", "like_count": 0, "author_name": "GTA6", "author_id": "0d145b4d5d17bf2ae68f72e2c32a934a", "author_is_anonymous": false, "child_comment": []}, {"url_token": "gta6-72", "headline": "", "is_advertiser": false, "comment_id": "3198976574", "reply_comment_id": "0", "reply_root_comment_id": "3198976574", "hot": false, "is_author": false, "is_author_top": false, "content": "11年买的速腾，现在还在开。。。", "like_count": 0, "author_name": "GTA6", "author_id": "0d145b4d5d17bf2ae68f72e2c32a934a", "author_is_anonymous": false, "child_comment": []}]