[{"url_token": "yi-diu-diu-8", "headline": "公众号：灿烂的美元", "is_advertiser": false, "comment_id": "4797074839", "reply_comment_id": "0", "reply_root_comment_id": "4797074839", "hot": false, "is_author": false, "is_author_top": false, "content": "喜欢这样的深度游。", "like_count": 1, "author_name": "伊丢丢", "author_id": "90cf83259ebad074db7276a6c025794b", "author_is_anonymous": false, "child_comment": [{"url_token": "hu-ming-wei-29", "headline": "银行“家”，公众号：捕金者说", "is_advertiser": false, "comment_id": "4797281344", "reply_comment_id": "4797074839", "reply_root_comment_id": "4797074839", "hot": false, "is_author": false, "is_author_top": false, "content": "对啊，常去常思考", "like_count": 0, "author_name": "胡明威", "author_id": "87ebb211fd4d8581974bd74a1f25315e", "author_is_anonymous": false}]}]