[{"url_token": "lu-deng-nan-hai-96", "headline": "", "is_advertiser": false, "comment_id": "618580135", "reply_comment_id": "0", "reply_root_comment_id": "618580135", "hot": false, "is_author": false, "is_author_top": false, "content": "<p>喜欢深色的</p>", "like_count": 8, "author_name": "知乎用户9lyt7f", "author_id": "aaa9e4934135e558bba903176350998d", "author_is_anonymous": false, "child_comment": []}, {"url_token": "nao-li-da-ren", "headline": "", "is_advertiser": false, "comment_id": "683783000", "reply_comment_id": "0", "reply_root_comment_id": "683783000", "hot": false, "is_author": false, "is_author_top": false, "content": "脚感特别不好！", "like_count": 4, "author_name": "脑力达人", "author_id": "2eb3aec1de59de96ecb864b785b36198", "author_is_anonymous": false, "child_comment": []}, {"url_token": "until-67-7", "headline": "", "is_advertiser": false, "comment_id": "818604218", "reply_comment_id": "0", "reply_root_comment_id": "818604218", "hot": false, "is_author": false, "is_author_top": false, "content": "安踏滑啊[捂脸][捂脸]", "like_count": 0, "author_name": "知乎用户5aK6iN", "author_id": "cda0aa2367ddbc8e02437a75325cfeb4", "author_is_anonymous": false, "child_comment": []}, {"url_token": "lang-shu-si", "headline": "喜欢得不到的.", "is_advertiser": false, "comment_id": "725126524", "reply_comment_id": "0", "reply_root_comment_id": "725126524", "hot": false, "is_author": false, "is_author_top": false, "content": "告诉我关键词也行啊", "like_count": 0, "author_name": "一只眠羊", "author_id": "aa156d5c7d2416f2a751c8a4401edb13", "author_is_anonymous": false, "child_comment": [{"url_token": "xia-zhi-chuang", "headline": "学习", "is_advertiser": false, "comment_id": "725328621", "reply_comment_id": "725126524", "reply_root_comment_id": "725126524", "hot": false, "is_author": false, "is_author_top": false, "content": "啊，，，，我不知道", "like_count": 1, "author_name": "hello", "author_id": "476f7b8f9f38087118bd46562b35f2b4", "author_is_anonymous": false}, {"url_token": "lang-shu-si", "headline": "喜欢得不到的.", "is_advertiser": false, "comment_id": "727485614", "reply_comment_id": "725328621", "reply_root_comment_id": "725126524", "hot": false, "is_author": false, "is_author_top": false, "content": "知道了，3q", "like_count": 0, "author_name": "一只眠羊", "author_id": "aa156d5c7d2416f2a751c8a4401edb13", "author_is_anonymous": false}, {"url_token": "a-lin-63-61", "headline": "", "is_advertiser": false, "comment_id": "726561317", "reply_comment_id": "725126524", "reply_root_comment_id": "725126524", "hot": false, "is_author": false, "is_author_top": false, "content": "大哥你直接把图片下载，去淘宝识图呀。", "like_count": 0, "author_name": "阿林", "author_id": "33873907423fa4efd921bf0937aa23a8", "author_is_anonymous": false}]}]