[{"url_token": "yi-ai-ma-34", "headline": "", "is_advertiser": false, "comment_id": "744293845", "reply_comment_id": "0", "reply_root_comment_id": "744293845", "hot": false, "is_author": false, "is_author_top": false, "content": "感觉这种不太精神", "like_count": 30, "author_name": "知乎用户0ilibI", "author_id": "84e717b749402892043ca4bdd6ef0804", "author_is_anonymous": false, "child_comment": [{"url_token": "henry-40-37", "headline": "工程系的金融党", "is_advertiser": false, "comment_id": "760924322", "reply_comment_id": "744293845", "reply_root_comment_id": "744293845", "hot": false, "is_author": false, "is_author_top": false, "content": "确实，第一眼就让我联想到弯腰驼背没睡醒", "like_count": 2, "author_name": "Meth", "author_id": "b709f5a2c7255be6f97704e0083aab98", "author_is_anonymous": false}, {"url_token": "zhu-zhu-28-40-34", "headline": "就爱瞎掰扯", "is_advertiser": false, "comment_id": "794222371", "reply_comment_id": "744293845", "reply_root_comment_id": "744293845", "hot": false, "is_author": false, "is_author_top": false, "content": "精神小伙必备豆豆鞋 关公脸谱T恤 还有一条勒到不行的裤子加皮带 和一个賊带感的bgm 必是这条该上最精神的小火", "like_count": 0, "author_name": "一男的", "author_id": "dde138bce3feab6bf97d0c9885f16138", "author_is_anonymous": false}, {"url_token": "xin-li-xiao-xi-xi", "headline": "追梦者", "is_advertiser": false, "comment_id": "773150930", "reply_comment_id": "758647306", "reply_root_comment_id": "744293845", "hot": false, "is_author": false, "is_author_top": false, "content": "v", "like_count": 0, "author_name": "心里笑嘻嘻", "author_id": "88eb607e1561ad9ac698492d57a14fb5", "author_is_anonymous": false}, {"url_token": "henry-40-37", "headline": "工程系的金融党", "is_advertiser": false, "comment_id": "761761451", "reply_comment_id": "761589021", "reply_root_comment_id": "744293845", "hot": false, "is_author": false, "is_author_top": false, "content": "“你这个年纪还睡得着觉，有点出息没有？！”", "like_count": 0, "author_name": "Meth", "author_id": "b709f5a2c7255be6f97704e0083aab98", "author_is_anonymous": false}, {"url_token": "jiu-ku-1", "headline": "街哲", "is_advertiser": false, "comment_id": "761589021", "reply_comment_id": "760924322", "reply_root_comment_id": "744293845", "hot": false, "is_author": false, "is_author_top": false, "content": "讲的是一个慵懒的感觉吧，我也不是很喜欢日系", "like_count": 0, "author_name": "救苦", "author_id": "a584870208e512a8934bd782d6532efc", "author_is_anonymous": false}, {"url_token": "yi-ai-ma-34", "headline": "", "is_advertiser": false, "comment_id": "760946210", "reply_comment_id": "760924322", "reply_root_comment_id": "744293845", "hot": false, "is_author": false, "is_author_top": false, "content": "就喜欢精神的孩子", "like_count": 0, "author_name": "知乎用户0ilibI", "author_id": "84e717b749402892043ca4bdd6ef0804", "author_is_anonymous": false}, {"url_token": "zou-ba-da-shu", "headline": "夏天过去了", "is_advertiser": false, "comment_id": "758647306", "reply_comment_id": "744293845", "reply_root_comment_id": "744293845", "hot": false, "is_author": false, "is_author_top": false, "content": "精神小伙气质在", "like_count": 0, "author_name": "Erebos", "author_id": "add221dfbfddbe3ded7e5d65b99a8ced", "author_is_anonymous": false}, {"url_token": "bu-wei-pang-guan-zhe", "headline": "", "is_advertiser": false, "comment_id": "758090451", "reply_comment_id": "744293845", "reply_root_comment_id": "744293845", "hot": false, "is_author": false, "is_author_top": false, "content": "旺旺一套", "like_count": 0, "author_name": "不为旁观者", "author_id": "019cd7024b62888943f7c8a5c9421931", "author_is_anonymous": false}]}, {"url_token": "zhu-zhu-28-40-34", "headline": "就爱瞎掰扯", "is_advertiser": false, "comment_id": "794221314", "reply_comment_id": "0", "reply_root_comment_id": "794221314", "hot": false, "is_author": false, "is_author_top": false, "content": "我想告诉你一个残酷的事实 同意的工装裤 同样的格子衫 同样的款 同样的颜色 还搭了个賊好看的鞋 但是这些对我都不重要 我要变得有气质其实只需要一个口罩就行了[为难][为难]", "like_count": 1, "author_name": "一男的", "author_id": "dde138bce3feab6bf97d0c9885f16138", "author_is_anonymous": false, "child_comment": []}, {"url_token": "pu-er-qing-nian", "headline": "双非二本工程硕士", "is_advertiser": false, "comment_id": "748209467", "reply_comment_id": "0", "reply_root_comment_id": "748209467", "hot": false, "is_author": false, "is_author_top": false, "content": "我可能审美有问题，这些欣赏不来。", "like_count": 24, "author_name": "June", "author_id": "65da93aebd04b7582fe907011bf026a0", "author_is_anonymous": false, "child_comment": []}, {"url_token": "yu-bai-dou-fu", "headline": "工程师", "is_advertiser": false, "comment_id": "744631606", "reply_comment_id": "0", "reply_root_comment_id": "744631606", "hot": false, "is_author": false, "is_author_top": false, "content": "你得考虑大众的平均颜值哇", "like_count": 10, "author_name": "鱼白豆腐", "author_id": "11172ba6d18ab326d32bf158e662a1ac", "author_is_anonymous": false, "child_comment": []}, {"url_token": "yong-chun-15", "headline": "", "is_advertiser": false, "comment_id": "748633498", "reply_comment_id": "0", "reply_root_comment_id": "748633498", "hot": false, "is_author": false, "is_author_top": false, "content": "上面还参考星爷，一推荐就跑偏", "like_count": 7, "author_name": "永春", "author_id": "c2576cb0f463ecbd70667f64de15a347", "author_is_anonymous": false, "child_comment": [{"url_token": "yong-chun-15", "headline": "", "is_advertiser": false, "comment_id": "751546404", "reply_comment_id": "751152398", "reply_root_comment_id": "748633498", "hot": false, "is_author": false, "is_author_top": false, "content": "星爷大部分是基本款，偶尔有一件带logo的基本款，你推荐的根本不一样", "like_count": 1, "author_name": "永春", "author_id": "c2576cb0f463ecbd70667f64de15a347", "author_is_anonymous": false}, {"url_token": "zgu-41", "headline": "有过烂脸经历，做护肤功课超认真。", "is_advertiser": false, "comment_id": "751152398", "reply_comment_id": "748633498", "reply_root_comment_id": "748633498", "hot": false, "is_author": false, "is_author_top": false, "content": "我参考的是那个时候的风格，但是也不能完全照搬呀，还是要符合现代审美的", "like_count": 0, "author_name": "文明小野花", "author_id": "6cc5254a8c092e063978336909bff8b6", "author_is_anonymous": false}]}, {"url_token": "liu-hao-59-85", "headline": "行年五十而知四十九年非", "is_advertiser": false, "comment_id": "748329433", "reply_comment_id": "0", "reply_root_comment_id": "748329433", "hot": false, "is_author": false, "is_author_top": false, "content": "你建议个   ，老子想怎么穿就怎么穿", "like_count": 7, "author_name": "轻刀快马", "author_id": "e197298d155e7ea890630506c9d60d87", "author_is_anonymous": false, "child_comment": [{"url_token": "zgu-41", "headline": "有过烂脸经历，做护肤功课超认真。", "is_advertiser": false, "comment_id": "749686057", "reply_comment_id": "748329433", "reply_root_comment_id": "748329433", "hot": false, "is_author": false, "is_author_top": false, "content": "阔以呀！我想怎么写就怎么写", "like_count": 1, "author_name": "文明小野花", "author_id": "6cc5254a8c092e063978336909bff8b6", "author_is_anonymous": false}]}, {"url_token": "wo-de-ming-43-59", "headline": "", "is_advertiser": false, "comment_id": "752711667", "reply_comment_id": "0", "reply_root_comment_id": "752711667", "hot": false, "is_author": false, "is_author_top": false, "content": "看着不精神呀，不知道是不是我审美和大家不一样", "like_count": 3, "author_name": "我的嗯嗯嗯", "author_id": "2fc0cca76a89622c4ec4b7598199e8a7", "author_is_anonymous": false, "child_comment": []}, {"url_token": "Ros_Nun", "headline": "", "is_advertiser": false, "comment_id": "748745364", "reply_comment_id": "0", "reply_root_comment_id": "748745364", "hot": false, "is_author": false, "is_author_top": false, "content": "虽然我身上就穿着其中一家的裤子，但还是得说这几家的衣服良莠不齐，主要是品质上容易踩坑", "like_count": 2, "author_name": "RosNun", "author_id": "d1bc35cc17a1e22935fe166e53d7c1e8", "author_is_anonymous": false, "child_comment": []}, {"url_token": "lue-lue-lue-65-50", "headline": "学生狗", "is_advertiser": false, "comment_id": "764527932", "reply_comment_id": "0", "reply_root_comment_id": "764527932", "hot": false, "is_author": false, "is_author_top": false, "content": "日系就是少年感吗？你的见识还算浅薄", "like_count": 1, "author_name": "略略略", "author_id": "f5385d2adeded8a0f53090c5b0783d6f", "author_is_anonymous": false, "child_comment": []}, {"url_token": "tongxin-bai", "headline": "", "is_advertiser": false, "comment_id": "753254021", "reply_comment_id": "0", "reply_root_comment_id": "753254021", "hot": false, "is_author": false, "is_author_top": false, "content": "我感觉喜欢这种baggy风格几乎是女生特有的审美偏好，并且南方女生多于北方女生", "like_count": 1, "author_name": "知乎用户y2WKV9", "author_id": "efb01157319d890c20527775805a16ee", "author_is_anonymous": false, "child_comment": []}]