{"id": "9414a44e3dbd34955670c926a109f3e7", "url_token": "bao-yan-mi-tu", "name": "抱盐米兔", "use_default_avatar": false, "avatar_url": "https://picx.zhimg.com/v2-0444c85e9a8bf7fbc78372624d41bd87_l.jpg?source=32738c0c", "avatar_url_template": "https://pica.zhimg.com/v2-0444c85e9a8bf7fbc78372624d41bd87.jpg?source=32738c0c", "is_org": false, "type": "people", "url": "https://www.zhihu.com/api/v4/people/bao-yan-mi-tu", "user_type": "people", "headline": "干着小活心怀天下的地青", "headline_render": "干着小活心怀天下的地青", "is_active": 1454367964, "description": "认输不可怕，只要能寻找到属于自己的道路就好！", "gender": 1, "is_advertiser": false, "ip_info": "IP 属地江苏", "vip_info": {"is_vip": false, "vip_type": 1, "rename_days": "60", "entrance_v2": null, "rename_frequency": 0, "rename_await_days": 0}, "badge": [], "badge_v2": {"title": "", "merged_badges": [], "detail_badges": [], "icon": "", "night_icon": ""}, "account_status": [], "message_thread_token": "9665118300", "allow_message": true, "is_following": false, "is_followed": false, "is_blocking": false, "is_blocked": false, "is_force_renamed": false, "follower_count": 13, "following_count": 98, "mutual_followees_count": 0, "answer_count": 107, "question_count": 0, "commercial_question_count": 0, "articles_count": 24, "favorite_count": 1, "favorited_count": 11, "pins_count": 7, "logs_count": 0, "voteup_count": 41, "thanked_count": 36, "hosted_live_count": 0, "participated_live_count": 0, "marked_answers_count": 0, "marked_answers_text": "", "following_columns_count": 5, "following_topic_count": 6, "following_question_count": 109, "following_favlists_count": 1, "vote_to_count": 0, "vote_from_count": 0, "thank_to_count": 0, "thank_from_count": 0, "available_medals_count": 0, "business": {"id": "19609879", "type": "topic", "url": "https://www.zhihu.com/api/v4/topics/19609879", "name": "非营利组织", "avatar_url": "https://pic1.zhimg.com/v2-94cfe37c5939760732d5dc8be9554449_l.jpg?source=32738c0c"}, "locations": [{"id": "19687937", "type": "topic", "url": "https://www.zhihu.com/api/v4/topics/19687937", "name": "北京市", "avatar_url": "https://pic1.zhimg.com/v2-40e779d5c5e6bcebda41e92d50594618_l.jpg?source=32738c0c"}], "employments": [{"job": {"id": "", "type": "topic", "url": "", "name": "替身T", "avatar_url": "https://picx.zhimg.com/e82bab09c_l.jpg?source=32738c0c"}, "company": {"id": "", "type": "topic", "url": "", "name": "心机组织", "avatar_url": "https://picx.zhimg.com/e82bab09c_l.jpg?source=32738c0c"}}], "educations": [{"school": {"id": "19580559", "type": "topic", "url": "https://www.zhihu.com/api/v4/topics/19580559", "name": "浙江大学", "avatar_url": "https://picx.zhimg.com/v2-296e14abbdce18ca325201220073a0e9_l.jpg?source=32738c0c"}}, {"school": {"id": "19563245", "type": "topic", "url": "https://www.zhihu.com/api/v4/topics/19563245", "name": "清华大学", "avatar_url": "https://pica.zhimg.com/v2-e2d2de874b3eae7354f6279bf05d3b98_l.jpg?source=32738c0c"}}], "cover_url": "", "avatar_hue": "", "is_bind_sina": false, "is_realname": true, "has_applying_column": false}