{"id": "737a77fa5d40bc8e77bbe95181a0984a", "url_token": "bi-bi-ai-chi-de-yu-mi-24", "name": "小李今天有点憨", "use_default_avatar": false, "avatar_url": "https://picx.zhimg.com/v2-6cdfbef8f283e757aabd5400c89aa6fa_l.jpg?source=32738c0c", "avatar_url_template": "https://pic1.zhimg.com/v2-6cdfbef8f283e757aabd5400c89aa6fa.jpg?source=32738c0c", "is_org": false, "type": "people", "url": "https://www.zhihu.com/api/v4/people/bi-bi-ai-chi-de-yu-mi-24", "user_type": "people", "headline": "民族主义者。", "headline_render": "民族主义者。", "is_active": 1473740771, "description": "狗腿子、伪女权、中医黑请退散。", "gender": -1, "is_advertiser": false, "ip_info": "IP 属地湖南", "vip_info": {"is_vip": false, "vip_type": 0, "rename_days": "0", "entrance_v2": null, "rename_frequency": 0, "rename_await_days": 0}, "badge": [], "badge_v2": {"title": "", "merged_badges": [], "detail_badges": [], "icon": "", "night_icon": ""}, "account_status": [], "message_thread_token": "8523019800", "allow_message": true, "is_following": false, "is_followed": false, "is_blocking": false, "is_blocked": false, "is_force_renamed": false, "follower_count": 15, "following_count": 109, "mutual_followees_count": 0, "answer_count": 0, "question_count": 0, "commercial_question_count": 0, "articles_count": 0, "favorite_count": 1, "favorited_count": 0, "pins_count": 0, "logs_count": 0, "voteup_count": 0, "thanked_count": 0, "hosted_live_count": 0, "participated_live_count": 1, "marked_answers_count": 0, "marked_answers_text": "", "following_columns_count": 5, "following_topic_count": 10, "following_question_count": 165, "following_favlists_count": 13, "vote_to_count": 0, "vote_from_count": 0, "thank_to_count": 0, "thank_from_count": 0, "available_medals_count": 0, "business": {"id": "", "type": "topic", "url": "", "name": "", "avatar_url": ""}, "locations": [], "employments": [], "educations": [], "cover_url": "https://picx.zhimg.com/v2-c26de7845ec141658a2ddcc5c43cd1b2_r.jpg?source=32738c0c", "avatar_hue": "", "is_bind_sina": false, "is_realname": true, "has_applying_column": false}