{"id": "9580dcac5380453ad4d90908abdf6c2f", "url_token": "bu-lao-xin", "name": "搅屎棍", "use_default_avatar": false, "avatar_url": "https://pic1.zhimg.com/v2-3c9981b38b09502d743e738c48466432_l.jpg?source=32738c0c", "avatar_url_template": "https://pic1.zhimg.com/v2-3c9981b38b09502d743e738c48466432.jpg?source=32738c0c", "is_org": false, "type": "people", "url": "https://www.zhihu.com/api/v4/people/bu-lao-xin", "user_type": "people", "headline": "搅局大赛第一名", "headline_render": "搅局大赛第一名", "is_active": 1, "description": "这是最好的时代也是最坏的时代！", "gender": 1, "is_advertiser": false, "ip_info": "IP 属地未知", "vip_info": {"is_vip": false, "vip_type": 1, "rename_days": "60", "entrance_v2": null, "rename_frequency": 0, "rename_await_days": 0}, "badge": [], "badge_v2": {"title": "", "merged_badges": [], "detail_badges": [], "icon": "", "night_icon": ""}, "account_status": [], "message_thread_token": "4980755500", "allow_message": true, "is_following": false, "is_followed": false, "is_blocking": false, "is_blocked": false, "is_force_renamed": false, "follower_count": 9, "following_count": 67, "mutual_followees_count": 0, "answer_count": 112, "question_count": 4, "commercial_question_count": 0, "articles_count": 1, "favorite_count": 4, "favorited_count": 1, "pins_count": 0, "logs_count": 9, "voteup_count": 18, "thanked_count": 12, "hosted_live_count": 0, "participated_live_count": 0, "marked_answers_count": 0, "marked_answers_text": "", "following_columns_count": 0, "following_topic_count": 13, "following_question_count": 230, "following_favlists_count": 6, "vote_to_count": 0, "vote_from_count": 0, "thank_to_count": 0, "thank_from_count": 0, "available_medals_count": 0, "business": {"id": "", "type": "topic", "url": "", "name": "临床医疗", "avatar_url": "https://pica.zhimg.com/e82bab09c_l.jpg?source=32738c0c"}, "locations": [{"id": "19615798", "type": "topic", "url": "https://www.zhihu.com/api/v4/topics/19615798", "name": "保定", "avatar_url": "https://pic1.zhimg.com/v2-fda6a0f1ee1954961b856cd6501949b5_l.jpg?source=32738c0c"}], "employments": [], "educations": [], "cover_url": "https://pica.zhimg.com/v2-a52bee8b3b40b49c1e0a5be4cd85f9cb_r.jpg?source=32738c0c", "avatar_hue": "", "is_bind_sina": false, "is_realname": true, "has_applying_column": false}