{"id": "4c511f00315edd6c7fd1cfb50f433544", "url_token": "chen-si-9-31", "name": "旱獭", "use_default_avatar": false, "avatar_url": "https://pica.zhimg.com/v2-0f8e800c39b8bfb4628173d03c9a340b_l.jpg?source=32738c0c", "avatar_url_template": "https://pic1.zhimg.com/v2-0f8e800c39b8bfb4628173d03c9a340b.jpg?source=32738c0c", "is_org": false, "type": "people", "url": "https://www.zhihu.com/api/v4/people/chen-si-9-31", "user_type": "people", "headline": "CFA/投资经理/银行理财/公募基金/年金投资/保险资管", "headline_render": "CFA/投资经理/银行理财/公募基金/年金投资/保险资管", "is_active": 1, "description": "CFA/投资经理/银行理财/保险资管/公募基金/年金投资/最近比较忙，若值乎忘记回答请重新发起", "gender": 1, "is_advertiser": false, "ip_info": "IP 属地北京", "vip_info": {"is_vip": true, "vip_type": 2, "rename_days": "60", "vip_icon": {"url": "https://picx.zhimg.com/v2-aa8a1823abfc46f14136f01d55224925.jpg?source=88ceefae", "night_mode_url": "https://picx.zhimg.com/v2-aa8a1823abfc46f14136f01d55224925.jpg?source=88ceefae"}, "entrance_v2": null, "rename_frequency": 5, "rename_await_days": 0}, "badge": [{"type": "best_answerer", "description": "优秀回答者", "topics": [{"id": "19579052", "type": "topic", "url": "https://www.zhihu.com/api/v4/topics/19579052", "name": "债券", "avatar_url": "https://pic1.zhimg.com/v2-be4cdf1db57f1323e0cad33eaa4d1734_l.jpg?source=32738c0c", "answer_count": 36, "article_count": 0, "creation_tip": "38 个创作"}]}], "badge_v2": {"title": "债券话题下的优秀答主", "merged_badges": [{"type": "best", "detail_type": "best", "title": "优秀答主", "description": "债券话题下的优秀答主", "url": "https://www.zhihu.com/question/48509984", "sources": [{"id": "19579052", "token": "19579052", "type": "topic", "url": "https://www.zhihu.com/topic/19579052", "name": "债券", "avatar_path": "v2-be4cdf1db57f1323e0cad33eaa4d1734", "avatar_url": "https://picx.zhimg.com/v2-be4cdf1db57f1323e0cad33eaa4d1734_720w.jpg?source=32738c0c", "description": "", "priority": 0}], "icon": "", "night_icon": "", "badge_status": "passed"}], "detail_badges": [{"type": "best", "detail_type": "best_answerer", "title": "优秀答主", "description": "债券话题下的优秀答主", "url": "https://www.zhihu.com/question/48509984", "sources": [{"id": "19579052", "token": "19579052", "type": "topic", "url": "https://www.zhihu.com/topic/19579052", "name": "债券", "avatar_path": "v2-be4cdf1db57f1323e0cad33eaa4d1734", "avatar_url": "https://picx.zhimg.com/v2-be4cdf1db57f1323e0cad33eaa4d1734_720w.jpg?source=32738c0c", "description": "", "priority": 0}], "icon": "https://picx.zhimg.com/v2-bf0eec3c31c8e866c468f60eb296696c_l.png?source=32738c0c", "night_icon": "https://pic1.zhimg.com/v2-c724649168d8f9d36d7c3d13140a2594_l.png?source=32738c0c", "badge_status": "passed"}], "icon": "https://pic1.zhimg.com/v2-bf0eec3c31c8e866c468f60eb296696c_l.png?source=32738c0c", "night_icon": "https://pic1.zhimg.com/v2-bf0eec3c31c8e866c468f60eb296696c_l.png?source=32738c0c"}, "account_status": [], "message_thread_token": "7359154600", "allow_message": true, "is_following": false, "is_followed": false, "is_blocking": false, "is_blocked": false, "is_force_renamed": false, "follower_count": 33702, "following_count": 328, "mutual_followees_count": 0, "answer_count": 122, "question_count": 0, "commercial_question_count": 0, "articles_count": 0, "favorite_count": 0, "favorited_count": 6199, "pins_count": 0, "logs_count": 100, "voteup_count": 4219, "thanked_count": 1169, "hosted_live_count": 0, "participated_live_count": 0, "marked_answers_count": 0, "marked_answers_text": "编辑推荐", "following_columns_count": 4, "following_topic_count": 32, "following_question_count": 544, "following_favlists_count": 4, "vote_to_count": 0, "vote_from_count": 0, "thank_to_count": 0, "thank_from_count": 0, "available_medals_count": 0, "business": {"id": "", "type": "topic", "url": "", "name": "资本投资", "avatar_url": "https://pic1.zhimg.com/e82bab09c_l.jpg?source=32738c0c"}, "locations": [{"id": "", "type": "topic", "url": "", "name": "哥谭市", "avatar_url": "https://pic1.zhimg.com/e82bab09c_l.jpg?source=32738c0c"}], "employments": [{"job": {"id": "19610746", "type": "topic", "url": "https://www.zhihu.com/api/v4/topics/19610746", "name": "投资经理", "avatar_url": "https://pica.zhimg.com/v2-65417a205cfef1d92c9dab388cc3e1df_l.jpg?source=32738c0c"}, "company": {"id": "", "type": "topic", "url": "", "name": "哥银理财", "avatar_url": "https://picx.zhimg.com/e82bab09c_l.jpg?source=32738c0c"}}], "educations": [], "cover_url": "https://picx.zhimg.com/v2-8d43559386980bea0cc4495cbf92fde8_r.jpg?source=32738c0c", "avatar_hue": "", "is_bind_sina": false, "is_realname": true, "has_applying_column": false}