{"id": "676930e19021140dd35293e17e1f62ff", "url_token": "guo-ming-fang-73", "name": "郭暝昉", "use_default_avatar": false, "avatar_url": "https://pica.zhimg.com/v2-83fdc18ffe6a2fb0f0e70ccc8b1b62a5_l.jpg?source=32738c0c", "avatar_url_template": "https://picx.zhimg.com/v2-83fdc18ffe6a2fb0f0e70ccc8b1b62a5.jpg?source=32738c0c", "is_org": false, "type": "people", "url": "https://www.zhihu.com/api/v4/people/guo-ming-fang-73", "user_type": "people", "headline": "国际低水平SCI灌溉区工作人员（劳务派遣）", "headline_render": "国际低水平SCI灌溉区工作人员（劳务派遣）", "is_active": 1, "description": "文能测字，武能防身", "gender": 1, "is_advertiser": false, "ip_info": "IP 属地江苏", "vip_info": {"is_vip": false, "vip_type": 1, "rename_days": "60", "entrance_v2": null, "rename_frequency": 0, "rename_await_days": 0}, "badge": [], "badge_v2": {"title": "", "merged_badges": [], "detail_badges": [], "icon": "", "night_icon": ""}, "account_status": [], "message_thread_token": "5652784300", "allow_message": true, "is_following": false, "is_followed": false, "is_blocking": false, "is_blocked": false, "is_force_renamed": false, "follower_count": 600, "following_count": 744, "mutual_followees_count": 0, "answer_count": 129, "question_count": 8, "commercial_question_count": 0, "articles_count": 12, "favorite_count": 13, "favorited_count": 719, "pins_count": 18, "logs_count": 36, "voteup_count": 809, "thanked_count": 163, "hosted_live_count": 0, "participated_live_count": 1, "marked_answers_count": 0, "marked_answers_text": "", "following_columns_count": 15, "following_topic_count": 96, "following_question_count": 546, "following_favlists_count": 2, "vote_to_count": 0, "vote_from_count": 0, "thank_to_count": 0, "thank_from_count": 0, "available_medals_count": 0, "business": {"id": "19558397", "type": "topic", "url": "https://www.zhihu.com/api/v4/topics/19558397", "name": "高等教育", "avatar_url": "https://picx.zhimg.com/v2-a530175cb3792d6560e4f2bdbadc2cdc_l.jpg?source=32738c0c"}, "locations": [{"id": "19730364", "type": "topic", "url": "https://www.zhihu.com/api/v4/topics/19730364", "name": "南京市", "avatar_url": "https://picx.zhimg.com/v2-40e779d5c5e6bcebda41e92d50594618_l.jpg?source=32738c0c"}, {"id": "19689163", "type": "topic", "url": "https://www.zhihu.com/api/v4/topics/19689163", "name": "杭州市", "avatar_url": "https://picx.zhimg.com/v2-40e779d5c5e6bcebda41e92d50594618_l.jpg?source=32738c0c"}, {"id": "", "type": "topic", "url": "", "name": "铜川市", "avatar_url": "https://pic1.zhimg.com/e82bab09c_l.jpg?source=32738c0c"}], "employments": [{"job": {"id": "19686088", "type": "topic", "url": "https://www.zhihu.com/api/v4/topics/19686088", "name": "讲师", "avatar_url": "https://picx.zhimg.com/v2-1164c9808b4a859319c828877b1d09eb_l.jpg?source=32738c0c"}, "company": {"id": "19695169", "type": "topic", "url": "https://www.zhihu.com/api/v4/topics/19695169", "name": "南京中医药大学", "avatar_url": "https://pic1.zhimg.com/v2-dc255277f3c27961b3dcedc9dbed0f1a_l.jpg?source=32738c0c"}}], "educations": [{"school": {"id": "19687769", "type": "topic", "url": "https://www.zhihu.com/api/v4/topics/19687769", "name": "浙江工商大学", "avatar_url": "https://pic1.zhimg.com/v2-1ac57c5569be22f115d13aeafacec0f6_l.jpg?source=32738c0c"}, "major": {"id": "19558693", "type": "topic", "url": "https://www.zhihu.com/api/v4/topics/19558693", "name": "食品科学", "avatar_url": "https://pic1.zhimg.com/37618940b_l.jpg?source=32738c0c"}, "entrance_year": 2017, "graduation_year": 2021, "diploma": 5}, {"school": {"id": "19687769", "type": "topic", "url": "https://www.zhihu.com/api/v4/topics/19687769", "name": "浙江工商大学", "avatar_url": "https://picx.zhimg.com/v2-1ac57c5569be22f115d13aeafacec0f6_l.jpg?source=32738c0c"}, "major": {"id": "20180633", "type": "topic", "url": "https://www.zhihu.com/api/v4/topics/20180633", "name": "食品科学与工程", "avatar_url": "https://pic1.zhimg.com/v2-5d07ee777ce91847cdb88b8a670cdeda_l.jpg?source=32738c0c"}, "entrance_year": 2014, "graduation_year": 2017, "diploma": 4}, {"school": {"id": "19921019", "type": "topic", "url": "https://www.zhihu.com/api/v4/topics/19921019", "name": "西北农林科技大学", "avatar_url": "https://picx.zhimg.com/v2-50d0d7e1f3d3177be5ed1432c0a03197_l.jpg?source=32738c0c"}, "major": {"id": "20180633", "type": "topic", "url": "https://www.zhihu.com/api/v4/topics/20180633", "name": "食品科学与工程", "avatar_url": "https://picx.zhimg.com/v2-5d07ee777ce91847cdb88b8a670cdeda_l.jpg?source=32738c0c"}, "entrance_year": 2010, "graduation_year": 2014, "diploma": 3}], "cover_url": "https://picx.zhimg.com/v2-acfb30a0470347758dbbe9e35753fe4d_r.jpg?source=32738c0c", "avatar_hue": "", "is_bind_sina": false, "is_realname": true, "has_applying_column": false}