{"id": "8f67b4ed424dc8f6e8464645d3686753", "url_token": "luo-hua-xiao-long", "name": "神经花骁龙", "use_default_avatar": false, "avatar_url": "https://picx.zhimg.com/bcfc19bcf3d34cdd0ced368a3863624d_l.jpg?source=32738c0c", "avatar_url_template": "https://pic1.zhimg.com/bcfc19bcf3d34cdd0ced368a3863624d.jpg?source=32738c0c", "is_org": false, "type": "people", "url": "https://www.zhihu.com/api/v4/people/luo-hua-xiao-long", "user_type": "people", "headline": "散人一个，爱好影视动画编导，养生保健，玄学等……", "headline_render": "散人一个，爱好影视动画编导，养生保健，玄学等……", "is_active": 1, "description": "杂乱无章，仅能博读广记而已……<br/>闲时饮茶乱谈古今<br/>忙时市井里一俗人", "gender": 1, "is_advertiser": false, "ip_info": "IP 属地未知", "vip_info": {"is_vip": false, "vip_type": 0, "rename_days": "0", "entrance_v2": null, "rename_frequency": 0, "rename_await_days": 0}, "badge": [], "badge_v2": {"title": "", "merged_badges": [], "detail_badges": [], "icon": "", "night_icon": ""}, "account_status": [], "message_thread_token": "4290876300", "allow_message": true, "is_following": false, "is_followed": false, "is_blocking": false, "is_blocked": false, "is_force_renamed": false, "follower_count": 9, "following_count": 41, "mutual_followees_count": 0, "answer_count": 46, "question_count": 32, "commercial_question_count": 0, "articles_count": 0, "favorite_count": 5, "favorited_count": 5, "pins_count": 0, "logs_count": 150, "voteup_count": 39, "thanked_count": 11, "hosted_live_count": 0, "participated_live_count": 0, "marked_answers_count": 0, "marked_answers_text": "", "following_columns_count": 0, "following_topic_count": 15, "following_question_count": 119, "following_favlists_count": 0, "vote_to_count": 0, "vote_from_count": 0, "thank_to_count": 0, "thank_from_count": 0, "available_medals_count": 0, "business": {"id": "", "type": "topic", "url": "", "name": "", "avatar_url": ""}, "locations": [], "employments": [], "educations": [], "cover_url": "", "avatar_hue": "", "is_bind_sina": false, "is_realname": true, "has_applying_column": false}