{"id": "157e99e303a389cf23e6c39f5038e3ee", "url_token": "wang-fu-gui-59-5-33", "name": "王富贵", "use_default_avatar": false, "avatar_url": "https://picx.zhimg.com/79ab7eb9271ea955272711b4a8169b0a_l.jpg?source=32738c0c", "avatar_url_template": "https://pic1.zhimg.com/79ab7eb9271ea955272711b4a8169b0a.jpg?source=32738c0c", "is_org": false, "type": "people", "url": "https://www.zhihu.com/api/v4/people/wang-fu-gui-59-5-33", "user_type": "people", "headline": "无知无畏学，留级生", "headline_render": "无知无畏学，留级生", "is_active": 1462331543, "description": "半瓶子晃荡的水平都不够", "gender": -1, "is_advertiser": false, "ip_info": "IP 属地河北", "vip_info": {"is_vip": false, "vip_type": 0, "rename_days": "0", "entrance_v2": null, "rename_frequency": 0, "rename_await_days": 0}, "badge": [], "badge_v2": {"title": "", "merged_badges": [], "detail_badges": [], "icon": "", "night_icon": ""}, "account_status": [], "message_thread_token": "6512768900", "allow_message": true, "is_following": false, "is_followed": false, "is_blocking": false, "is_blocked": false, "is_force_renamed": false, "follower_count": 51, "following_count": 210, "mutual_followees_count": 0, "answer_count": 83, "question_count": 2, "commercial_question_count": 0, "articles_count": 0, "favorite_count": 15, "favorited_count": 26, "pins_count": 1, "logs_count": 7, "voteup_count": 928, "thanked_count": 61, "hosted_live_count": 0, "participated_live_count": 0, "marked_answers_count": 0, "marked_answers_text": "", "following_columns_count": 4, "following_topic_count": 31, "following_question_count": 222, "following_favlists_count": 1, "vote_to_count": 0, "vote_from_count": 0, "thank_to_count": 0, "thank_from_count": 0, "available_medals_count": 0, "business": {"id": "", "type": "topic", "url": "", "name": "", "avatar_url": ""}, "locations": [{"id": "19550828", "type": "topic", "url": "https://www.zhihu.com/api/v4/topics/19550828", "name": "北京", "avatar_url": "https://pica.zhimg.com/v2-cedb40dc1dff4e5b2f8815c185f05111_l.jpg?source=32738c0c"}], "employments": [], "educations": [{"school": {"id": "", "type": "topic", "url": "", "name": "清华池", "avatar_url": "https://picx.zhimg.com/e82bab09c_l.jpg?source=32738c0c"}, "diploma": 0}], "cover_url": "", "avatar_hue": "", "is_bind_sina": false, "is_realname": true, "has_applying_column": false}